dev_pipeline-0.4.0.dist-info/DESCRIPTION.rst
dev_pipeline-0.4.0.dist-info/METADATA
dev_pipeline-0.4.0.dist-info/RECORD
dev_pipeline-0.4.0.dist-info/WHEEL
dev_pipeline-0.4.0.dist-info/entry_points.txt
dev_pipeline-0.4.0.dist-info/metadata.json
dev_pipeline-0.4.0.dist-info/top_level.txt
devpipeline/__init__.py
devpipeline/driver.py
