Metadata-Version: 2.0
Name: dev-pipeline
Version: 0.4.0
Summary: Manage projects spread across multiple repositories
Home-page: https://github.com/dev-pipeline/dev-pipeline
Author: Stephen Newell
Author-email: UNKNOWN
License: BSD-2
Platform: UNKNOWN
Classifier: Development Status :: 2 - Pre-Alpha
Classifier: Environment :: Console
Classifier: Intended Audience :: Developers
Classifier: License :: OSI Approved :: BSD License
Classifier: Topic :: Software Development
Classifier: Topic :: Utilities
Requires-Dist: dev-pipeline-bootstrap (>=0.4.0)
Requires-Dist: dev-pipeline-build (>=0.4.0)
Requires-Dist: dev-pipeline-build-order (>=0.4.0)
Requires-Dist: dev-pipeline-cmake (>=0.4.0)
Requires-Dist: dev-pipeline-configure (>=0.4.0)
Requires-Dist: dev-pipeline-core (>=0.4.0)
Requires-Dist: dev-pipeline-git (>=0.4.0)
Requires-Dist: dev-pipeline-scm (>=0.4.0)
